ios2andres.py
ios2andres-0.1.8.dist-info/DESCRIPTION.rst
ios2andres-0.1.8.dist-info/METADATA
ios2andres-0.1.8.dist-info/RECORD
ios2andres-0.1.8.dist-info/WHEEL
ios2andres-0.1.8.dist-info/entry_points.txt
ios2andres-0.1.8.dist-info/metadata.json
ios2andres-0.1.8.dist-info/namespace_packages.txt
ios2andres-0.1.8.dist-info/top_level.txt
