Metadata-Version: 2.0
Name: ios2andres
Version: 0.1.8
Summary: iOS to Android Resource Renamer
Home-page: https://github.com/jordanjoz1/ios2androidres
Author: Jordan Jozwiak
Author-email: support@jozapps.com
License: MIT
Keywords: android resources ios convert
Platform: UNKNOWN
Classifier: License :: OSI Approved :: BSD License
Classifier: Intended Audience :: Developers
Classifier: Programming Language :: Python
